odoo8_addon_l10n_it_esigibilita_iva-8.0.2.0.0-nspkg.pth
odoo_addons/l10n_it_esigibilita_iva/README.rst
odoo_addons/l10n_it_esigibilita_iva/__init__.py
odoo_addons/l10n_it_esigibilita_iva/__openerp__.py
odoo_addons/l10n_it_esigibilita_iva/i18n/it.po
odoo_addons/l10n_it_esigibilita_iva/i18n/l10n_it_esigibilita_iva.pot
odoo_addons/l10n_it_esigibilita_iva/i18n/sl.po
odoo_addons/l10n_it_esigibilita_iva/models/__init__.py
odoo_addons/l10n_it_esigibilita_iva/models/account.py
odoo_addons/l10n_it_esigibilita_iva/static/description/icon.png
odoo_addons/l10n_it_esigibilita_iva/views/account_view.xml
odoo8_addon_l10n_it_esigibilita_iva-8.0.2.0.0.dist-info/METADATA
odoo8_addon_l10n_it_esigibilita_iva-8.0.2.0.0.dist-info/WHEEL
odoo8_addon_l10n_it_esigibilita_iva-8.0.2.0.0.dist-info/namespace_packages.txt
odoo8_addon_l10n_it_esigibilita_iva-8.0.2.0.0.dist-info/top_level.txt
odoo8_addon_l10n_it_esigibilita_iva-8.0.2.0.0.dist-info/RECORD
