Metadata-Version: 2.1
Name: odoo8-addon-l10n-it-esigibilita-iva
Version: 8.0.2.0.0
Summary: Esigibilità IVA
Home-page: https://www.odoo-italia.net
Author: Openforce di Camilli Alessandro, Odoo Community Association (OCA)
Author-email: support@odoo-community.org
License: LGPL-3
Platform: UNKNOWN
Classifier: Programming Language :: Python
Classifier: Framework :: Odoo
Classifier: License :: OSI Approved :: GNU Lesser General Public License v3 (LGPLv3)
Requires-Python: ~=2.7
Requires-Dist: odoo (<9.0a,>=8.0a)
